<annotation>
	<folder></folder>
	<filename>20240501_030126_025_jpg.rf.c078bedba98b79e98a9805719e219943.jpg</filename>
	<path>20240501_030126_025_jpg.rf.c078bedba98b79e98a9805719e219943.jpg</path>
	<source>
		<database>roboflow.com</database>
	</source>
	<size>
		<width>640</width>
		<height>640</height>
		<depth>3</depth>
	</size>
	<segmented>0</segmented>
	<object>
		<name>Side-Fracture</name>
		<pose>Unspecified</pose>
		<truncated>0</truncated>
		<difficult>0</difficult>
		<occluded>0</occluded>
		<bndbox>
			<xmin>76</xmin>
			<xmax>432</xmax>
			<ymin>57</ymin>
			<ymax>475</ymax>
		</bndbox>
	</object>
</annotation>
