<annotation>
	<folder></folder>
	<filename>20240501_021849_010_jpg.rf.8d5637d197c5aad4635f9e68644fe193.jpg</filename>
	<path>20240501_021849_010_jpg.rf.8d5637d197c5aad4635f9e68644fe193.jpg</path>
	<source>
		<database>roboflow.com</database>
	</source>
	<size>
		<width>640</width>
		<height>640</height>
		<depth>3</depth>
	</size>
	<segmented>0</segmented>
	<object>
		<name>Side_Rust</name>
		<pose>Unspecified</pose>
		<truncated>0</truncated>
		<difficult>0</difficult>
		<occluded>0</occluded>
		<bndbox>
			<xmin>94</xmin>
			<xmax>458</xmax>
			<ymin>89</ymin>
			<ymax>559</ymax>
		</bndbox>
	</object>
</annotation>
